cyclepath_classifier/__init__.py
cyclepath_classifier/__main__.py
cyclepath_classifier/classifier.py
cyclepath_classifier/complexity.py
cyclepath_classifier/graph.py
cyclepath_classifier/instances.py
cyclepath_classifier/problem.py
cyclepath_classifier/util.py
cyclepath_classifier-0.2.1.dist-info/AUTHORS
cyclepath_classifier-0.2.1.dist-info/LICENSE
cyclepath_classifier-0.2.1.dist-info/METADATA
cyclepath_classifier-0.2.1.dist-info/WHEEL
cyclepath_classifier-0.2.1.dist-info/top_level.txt
cyclepath_classifier-0.2.1.dist-info/RECORD
