Metadata-Version: 2.1
Name: cyclepath-classifier
Version: 0.2.1
Summary: A command-line tool for automatically calculating round complexity of LCL problems in cycles and paths based on their description in the node-edge-checkable formalism
Home-page: https://github.com/AleksTeresh/cyclepath-classifier
Author: Aleksandr Tereshchenko
Author-email: aleksandr.tereshch@gmail.com
License: MIT
Platform: UNKNOWN
Classifier: License :: OSI Approved :: MIT License
Classifier: Programming Language :: Python :: 3
Classifier: Programming Language :: Python :: 3.8
